MANIFEST.in
README.md
setup.cfg
setup.py
almastorage/__init__.py
almastorage/admin.py
almastorage/api.py
almastorage/forms.py
almastorage/models.py
almastorage/tests.py
almastorage/urls.py
almastorage/views.py
almastorage/migrations/0001_initial.py
almastorage/migrations/0001_initial.pyc
almastorage/migrations/0002_auto__del_unique_swiftcontainer_service_slug.pyc
almastorage/migrations/__init__.py
almastorage/migrations/__init__.pyc
almastorage/utils/__init__.py
almastorage/utils/__init__.pyc
almastorage/utils/default_file.py
almastorage/utils/default_file.pyc
almastorage/utils/temp_generator.py
almastorage/utils/temp_generator.pyc
django_almastorage.egg-info/PKG-INFO
django_almastorage.egg-info/SOURCES.txt
django_almastorage.egg-info/dependency_links.txt
django_almastorage.egg-info/not-zip-safe
django_almastorage.egg-info/requires.txt
django_almastorage.egg-info/top_level.txt