Metadata-Version: 1.1
Name: django-almastorage
Version: 0.4
Summary: A simple Django app to use SwiftStack Storage
Home-page: https://github.com/aaannnyyy/django-almastorage
Author: Nurlan Abyken
Author-email: abyken.nurlan@gmail.com
License: UNKNOWN
Platform: UNKNOWN
Classifier: Environment :: Web Environment
Classifier: Framework :: Django
Classifier: Intended Audience :: Developers
Classifier: Operating System :: OS Independent
Classifier: Programming Language :: Python
Classifier: Programming Language :: Python :: 2.6
Classifier: Programming Language :: Python :: 2.7
Classifier: Topic :: Utilities
